sparkdesk_api/__init__.py
sparkdesk_api/core.py
sparkdesk_api/utils.py
sparkdesk_web/__init__.py
sparkdesk_web/core.py
sparkdesk_web/utils.py
sparkdesk_web/web.py
sparkdesk_api-1.5.0.dist-info/LICENSE
sparkdesk_api-1.5.0.dist-info/METADATA
sparkdesk_api-1.5.0.dist-info/WHEEL
sparkdesk_api-1.5.0.dist-info/top_level.txt
sparkdesk_api-1.5.0.dist-info/RECORD
