Metadata-Version: 2.1
Name: sparkdesk-api
Version: 1.5.0
Summary: sparkdesk-api 讯飞星火大模型api
Home-page: https://github.com/HildaM/sparkdesk-api
Author: HildaM
Author-email: Hilda_quan@163.com
License: GNU General Public License v3.0
Classifier: Programming Language :: Python :: 3
Classifier: License :: OSI Approved :: MIT License
Classifier: Operating System :: OS Independent
License-File: LICENSE
